CHANGES.txt
MANIFEST.in
README.txt
bootstrap.py
setup.py
src/gocept/__init__.py
src/gocept.thermosnake.egg-info/PKG-INFO
src/gocept.thermosnake.egg-info/SOURCES.txt
src/gocept.thermosnake.egg-info/dependency_links.txt
src/gocept.thermosnake.egg-info/entry_points.txt
src/gocept.thermosnake.egg-info/namespace_packages.txt
src/gocept.thermosnake.egg-info/not-zip-safe
src/gocept.thermosnake.egg-info/requires.txt
src/gocept.thermosnake.egg-info/top_level.txt
src/gocept/thermosnake/README.txt
src/gocept/thermosnake/__init__.py
src/gocept/thermosnake/check_temp_ts.py