Metadata-Version: 1.0
Name: gocept.thermosnake
Version: 0.7
Summary: Nagios check script for temperature monitoring using thermosnake hardware
Home-page: http://gocept.com
Author: Daniel Havlik
Author-email: dh@gocept.com
License: GPL
Keywords: nagios thermosnake
Platform: UNKNOWN
Classifier: Programming Language :: Python
